md2book/__init__.py
md2book/config.py
md2book/main.py
md2book/start.py
md2book/templates.py
md2book/convert/__init__.py
md2book/convert/convert.py
md2book/convert/forms.py
md2book/convert/forms_stored.py
md2book/convert/forms_text.py
md2book/convert/pipelines.py
md2book/data/default_aliases.yml
md2book/data/default_settings.yml
md2book/data/generated_default_settings.yml
md2book/data/fonts/1942/1942-normal-normal.ttf
md2book/data/fonts/1942/Freeware License.txt
md2book/data/fonts/1942/preview.png
md2book/data/fonts/allura/SIL Open Font License.txt
md2book/data/fonts/allura/allura-normal-normal.otf
md2book/data/fonts/allura/preview.png
md2book/data/fonts/aquiline/Manfred Klein License.txt
md2book/data/fonts/aquiline/aquiline-normal-normal.ttf
md2book/data/fonts/aquiline/preview.png
md2book/data/fonts/calligraffiti/Apache License.txt
md2book/data/fonts/calligraffiti/calligraffiti-normal-normal.ttf
md2book/data/fonts/calligraffiti/preview.png
md2book/data/fonts/caslon/SIL Open Font License.txt
md2book/data/fonts/caslon/_librecaslontext-regular.otf
md2book/data/fonts/caslon/caslon-italic-normal.otf
md2book/data/fonts/caslon/caslon-normal-bold.otf
md2book/data/fonts/caslon/caslon-normal-normal.otf
md2book/data/fonts/caslon/preview.png
md2book/data/fonts/conspiracy/CONSPR__.TTF
md2book/data/fonts/conspiracy/conspiracy-normal-bold.ttf
md2book/data/fonts/conspiracy/conspiracy-normal-normal.ttf
md2book/data/fonts/conspiracy/preview.png
md2book/data/fonts/conspiracy/readme.txt
md2book/data/fonts/drakon/drakon-normal-normal.ttf
md2book/data/fonts/drakon/preview.jpg
md2book/data/fonts/dwarves/dwarves-normal-normal.ttf
md2book/data/fonts/dwarves/preview.jpg
md2book/data/fonts/garamond/SIL Open Font License.txt
md2book/data/fonts/garamond/_EBGaramond-Initials.otf
md2book/data/fonts/garamond/_EBGaramond-InitialsF1.otf
md2book/data/fonts/garamond/_EBGaramond-InitialsF2.otf
md2book/data/fonts/garamond/_EBGaramond12-AllSC.otf
md2book/data/fonts/garamond/_EBGaramondSC12-Regular.otf
md2book-0.1.3.dist-info/LICENSE
md2book-0.1.3.dist-info/METADATA
md2book-0.1.3.dist-info/WHEEL
md2book-0.1.3.dist-info/entry_points.txt
md2book-0.1.3.dist-info/top_level.txt
md2book-0.1.3.dist-info/RECORD
