Metadata-Version: 2.1
Name: md2book
Version: 0.1.3
Summary: Convert markdown files to beautiful books using a simple configuration file
Home-page: https://github.com/webalorn/md2book
Author: webalorn
Author-email: webalorn@gmail.com
Project-URL: Documentation, https://github.com/webalorn/md2book/wiki
Project-URL: Source, https://github.com/webalorn/md2book
Classifier: Programming Language :: Python :: 3
Classifier: License :: OSI Approved :: MIT License
Classifier: Operating System :: OS Independent
Requires-Python: >=3
License-File: LICENSE
Requires-Dist: pyyaml (>=5.2)
Requires-Dist: markdown (>=3.2)
Requires-Dist: pdfkit (>=0.6.1)
Requires-Dist: python-docx (>-0.8.10)
